montyledger/__init__.py
montyledger/monty/__init__.py
montyledger/monty/engine.py
montyledger/monty/limit.py
montyledger/monty/schema.py
montyledger/monty/store.py
montyledger/store_classes/__init__.py
montyledger/store_classes/kv.py
montyledger/store_functions/__init__.py
montyledger/store_functions/store_generic_functions.py
montyledger-0.1.2.dist-info/METADATA
montyledger-0.1.2.dist-info/WHEEL
montyledger-0.1.2.dist-info/top_level.txt
montyledger-0.1.2.dist-info/RECORD
