Metadata-Version: 2.1
Name: montyledger
Version: 0.1.2
Summary: monty client
Author: MontyGovernance
Author-email: eugene.and.monty@gmail.com
Classifier: Programming Language :: Python :: 3
Classifier: License :: OSI Approved :: MIT License
Classifier: Operating System :: OS Independent
Requires-Python: >=3.9
Requires-Dist: orjson
Requires-Dist: xxhash
Requires-Dist: asyncio
Requires-Dist: typing
